[
  {
    "Nombre": "Mariano",
    "Apellido": "Ruiz",
    "DNI": "34265987",
    "Correo": "mar@gmail.com",
    "Telefono": "11765298",
    "Direccion": "Calle 254",
    "ID": "22",
    "Clave": "22",
    "Nivel": "Titular"
  },
  {
    "Nombre": "Marta",
    "Apellido": "Ramirez",
    "DNI": "29763567",
    "Correo": "marta@gmail.com",
    "Telefono": "11876209",
    "Direccion": "calle 1028",
    "ID": "942217",
    "Clave": "5DqniWjH",
    "Nivel": "Titular"
  },
  {
    "Nombre": "Mauro",
    "Apellido": "Silva",
    "DNI": "37987562",
    "Correo": "mau@gmail.com",
    "Telefono": "11876265",
    "Direccion": "Calle 6729",
    "ID": "798612",
    "Clave": "W41Llnc3",
    "Nivel": "Ayudante"
  },
  {
    "Nombre": "Lilia",
    "Apellido": "Alvarez",
    "DNI": "36278098",
    "Correo": "lili@gmail.com",
    "Telefono": "11872653",
    "Direccion": "Calle 2018",
    "ID": "518805",
    "Clave": "ImZ3dIxr",
    "Nivel": "JefeDeCatedra"
  },
  {
    "Nombre": "sdfsdf",
    "Apellido": "wrer",
    "DNI": "234324",
    "Correo": "sdf@gmail.com",
    "Telefono": "234234",
    "Direccion": "234324",
    "ID": "998032",
    "Clave": "55Yburfj",
    "Nivel": "Titular"
  },
  {
    "Nombre": "fdgdf",
    "Apellido": "dfgdfg",
    "DNI": "345545",
    "Correo": "dfg@gmail.com",
    "Telefono": "234",
    "Direccion": "234",
    "ID": "668672",
    "Clave": "NN1MVqsE",
    "Nivel": "Ayudante"
  }
]